odoo/addons/account_payment_show_invoice/README.rst
odoo/addons/account_payment_show_invoice/__init__.py
odoo/addons/account_payment_show_invoice/__manifest__.py
odoo/addons/account_payment_show_invoice/i18n/account_payment_show_invoice.pot
odoo/addons/account_payment_show_invoice/i18n/de.po
odoo/addons/account_payment_show_invoice/models/__init__.py
odoo/addons/account_payment_show_invoice/models/account_payment.py
odoo/addons/account_payment_show_invoice/readme/CONTRIBUTORS.rst
odoo/addons/account_payment_show_invoice/readme/DESCRIPTION.rst
odoo/addons/account_payment_show_invoice/readme/USAGE.rst
odoo/addons/account_payment_show_invoice/static/description/icon.png
odoo/addons/account_payment_show_invoice/static/description/index.html
odoo/addons/account_payment_show_invoice/static/description/payments_view.png
odoo/addons/account_payment_show_invoice/views/account_payment_view.xml
odoo11_addon_account_payment_show_invoice-11.0.1.0.0.99.dev7.dist-info/METADATA
odoo11_addon_account_payment_show_invoice-11.0.1.0.0.99.dev7.dist-info/WHEEL
odoo11_addon_account_payment_show_invoice-11.0.1.0.0.99.dev7.dist-info/top_level.txt
odoo11_addon_account_payment_show_invoice-11.0.1.0.0.99.dev7.dist-info/RECORD
